setup.py
StatesofUSA.egg-info/PKG-INFO
StatesofUSA.egg-info/SOURCES.txt
StatesofUSA.egg-info/dependency_links.txt
StatesofUSA.egg-info/top_level.txt
statesofusa/__init__.py
statesofusa/app.py
statesofusa/auth.py
statesofusa/auth_models.py
statesofusa/constants.py
statesofusa/main.py
statesofusa/response.py
statesofusa/rest_base.py
statesofusa/us_states_api.py