Metadata-Version: 1.1
Name: StatesofUSA
Version: 0.1
Summary: An API built on  Flask-RESTful that returns with the names of all the states in USA.
Home-page: UNKNOWN
Author: Isham
Author-email: eyash.27@gmail.com
License: GPL
Keywords: states usa america
Platform: UNKNOWN
Classifier: Development Status :: 2 - Pre-Alpha
Classifier: Topic :: Utilities
Classifier: License :: OSI Approved :: GNU General Public License (GPL)
Classifier: Operating System :: Unix
